quicksectx/quicksectx.cpp
quicksectx/quicksectx.cpython-311-darwin.so
quicksectx/quicksectx.pxd
quicksectx/__init__.py
quicksectx/quicksectx.pyx
quicksectx-0.4.0.dist-info/RECORD
quicksectx-0.4.0.dist-info/LICENSE
quicksectx-0.4.0.dist-info/WHEEL
quicksectx-0.4.0.dist-info/top_level.txt
quicksectx-0.4.0.dist-info/METADATA
quicksect/quicksect.cpython-311-darwin.so
quicksect/quicksect.pyx
quicksect/__init__.py
quicksect/quicksect.cpp
