Metadata-Version: 2.1
Name: quicksectx
Version: 0.4.0
Summary: Quicksect is a fast python / cython implementation of interval search.
Home-page: https://github.com/jianlins/quicksectx
Author: Brent Pedersen,Jianlin Shi
Author-email: Jianlin <jianlinshi.cn@gmail.com>
License: The MIT License (MIT)
Project-URL: Source, https://github.com/jianlins/quicksectx
Keywords: quicksectx,interval search,interval tree
Classifier: License :: OSI Approved :: MIT License
Classifier: Programming Language :: Python :: 3
Requires-Python: >=3.8
License-File: LICENSE
Requires-Dist: Cython<=3.0.11,>=0.25
